hiddenbayes/__init__.py
hiddenbayes/hnb.py
hiddenbayes-0.1.0.dist-info/LICENSE
hiddenbayes-0.1.0.dist-info/METADATA
hiddenbayes-0.1.0.dist-info/WHEEL
hiddenbayes-0.1.0.dist-info/top_level.txt
hiddenbayes-0.1.0.dist-info/RECORD
