Metadata-Version: 2.2
Name: hiddenbayes
Version: 0.1.0
Summary: A Hidden Naive Bayes library, it will give support to scikit-learn
Author-email: Angel Cervera Ronda <angelcerveraronda@gmail.com>
License: BSD-3-Clause
Project-URL: Homepage, https://github.com/C4RBON0/hiddenbayes
Classifier: Programming Language :: Python :: 3
Classifier: License :: OSI Approved :: BSD License
Classifier: Operating System :: OS Independent
Requires-Python: >=3.7
License-File: LICENSE
